bitget_api_client/__init__.py
bitget_api_client/client.py
bitget_api_client/modules/__init__.py
bitget_api_client/modules/affiliate.py
bitget_api_client/modules/broker.py
bitget_api_client/modules/common.py
bitget_api_client/modules/contract.py
bitget_api_client/modules/copytrading.py
bitget_api_client/modules/earn.py
bitget_api_client/modules/exceptions.py
bitget_api_client/modules/instloan.py
bitget_api_client/modules/margin.py
bitget_api_client/modules/spot.py
bitget_api_client/modules/uta.py
bitget_api_client/modules/websocket_client.py
bitget_api_client-0.1.8.dist-info/licenses/LICENSE
bitget_api_client-0.1.8.dist-info/METADATA
bitget_api_client-0.1.8.dist-info/WHEEL
bitget_api_client-0.1.8.dist-info/top_level.txt
bitget_api_client-0.1.8.dist-info/RECORD
