Metadata-Version: 2.4
Name: bitget-api-client
Version: 0.1.8
Summary: A Python client for the Bitget API V2
Author-email: tty666 <theentity666@gmail.com>
Project-URL: Homepage, https://github.com/tty666/bitget-api-client
Project-URL: Bug Tracker, https://github.com/tty666/bitget-api-client/issues
Classifier: Programming Language :: Python :: 3
Classifier: License :: OSI Approved :: MIT License
Classifier: Operating System :: OS Independent
Requires-Python: >=3.9
License-File: LICENSE
Requires-Dist: aiohttp
Requires-Dist: requests
Requires-Dist: websockets
Dynamic: license-file
